cvxpylayers/__init__.py
cvxpylayers/py.typed
cvxpylayers/interfaces/__init__.py
cvxpylayers/interfaces/clarabel_if.py
cvxpylayers/interfaces/cuclarabel_if.py
cvxpylayers/interfaces/diffcp_if.py
cvxpylayers/interfaces/moreau_if.py
cvxpylayers/interfaces/mpax_if.py
cvxpylayers/jax/__init__.py
cvxpylayers/jax/cvxpylayer.py
cvxpylayers/mlx/__init__.py
cvxpylayers/mlx/cvxpylayer.py
cvxpylayers/torch/__init__.py
cvxpylayers/torch/cvxpylayer.py
cvxpylayers/utils/parse_args.py
cvxpylayers/utils/solver_utils.py
cvxpylayers-1.0.0.dist-info/METADATA
cvxpylayers-1.0.0.dist-info/WHEEL
cvxpylayers-1.0.0.dist-info/licenses/LICENSE
cvxpylayers-1.0.0.dist-info/RECORD
