Metadata-Version: 2.4
Name: cvxpylayers
Version: 1.0.0
Summary: Solve and differentiate Convex Optimization problems on the GPU
Project-URL: Homepage, https://github.com/cvxpy/cvxpylayers
Project-URL: Repository, https://github.com/cvxpy/cvxpylayers.git
Project-URL: Documentation, https://github.com/cvxpy/cvxpylayers
Project-URL: Bug Tracker, https://github.com/cvxpy/cvxpylayers/issues
Author: A. Agrawal, B. Amos, S. Barratt, S. Diamond
Maintainer-email: "P. Nobel" <parthnobel@berkeley.edu>
License: Apache-2.0
License-File: LICENSE
Keywords: convex optimization,cvxpy,mathematical programming
Classifier: Development Status :: 5 - Production/Stable
Classifier: Intended Audience :: Developers
Classifier: Intended Audience :: Science/Research
Classifier: License :: OSI Approved :: Apache Software License
Classifier: Operating System :: OS Independent
Classifier: Programming Language :: Python :: 3
Classifier: Programming Language :: Python :: 3.11
Classifier: Programming Language :: Python :: 3.12
Classifier: Programming Language :: Python :: 3.13
Classifier: Topic :: Scientific/Engineering :: Artificial Intelligence
Classifier: Topic :: Scientific/Engineering :: Mathematics
Classifier: Topic :: Software Development :: Libraries :: Python Modules
Requires-Python: >=3.11
Requires-Dist: cvxpy>=1.7.4
Requires-Dist: diffcp>=1.1.0
Requires-Dist: numpy>=1.22.4
Requires-Dist: scipy>=1.13.0
Provides-Extra: all
Requires-Dist: diffqcp>=0.4.4; extra == 'all'
Requires-Dist: jax>=0.4.0; extra == 'all'
Requires-Dist: jaxlib>=0.4.0; extra == 'all'
Requires-Dist: mlx-metal==0.27.1; extra == 'all'
Requires-Dist: mlx==0.27.1; extra == 'all'
Requires-Dist: torch>=2.0.0; extra == 'all'
Provides-Extra: jax
Requires-Dist: jax>=0.4.0; extra == 'jax'
Requires-Dist: jaxlib>=0.4.0; extra == 'jax'
Provides-Extra: metal
Requires-Dist: mlx-metal==0.27.1; extra == 'metal'
Provides-Extra: mlx
Requires-Dist: mlx==0.27.1; extra == 'mlx'
Provides-Extra: torch
Requires-Dist: diffcp>=1.1.0; extra == 'torch'
Requires-Dist: torch>=2.0.0; extra == 'torch'
